gpac/_PAC.py
gpac/__init__.py
gpac/core/_BandPassFilter.py
gpac/core/_Hilbert.py
gpac/core/_ModulationIndex.py
gpac/core/_ModulationIndex_v01-roll.py
gpac/core/__init__.py
gpac/core/_BandPassFilters/_PooledBandPassFilter.py
gpac/core/_BandPassFilters/_StaticBandPassFilter.py
gpac/core/_BandPassFilters/__init__.py
gpac/dataset/_SyntheticDataGenerator.py
gpac/dataset/_SyntheticPACDataset.py
gpac/dataset/__init__.py
gpac/dataset/_configs.py
gpac/dataset/_generate_pac_dataset.py
gpac/utils/__init__.py
gpac/utils/_config.py
gpac/utils/_exceptions.py
gpac/utils/_profiler.py
gpac/utils/compare.py
gpu_pac-0.3.4.dist-info/licenses/LICENSE
gpu_pac-0.3.4.dist-info/METADATA
gpu_pac-0.3.4.dist-info/WHEEL
gpu_pac-0.3.4.dist-info/top_level.txt
gpu_pac-0.3.4.dist-info/RECORD
