Metadata-Version: 2.4
Name: gpu-pac
Version: 0.3.4
Summary: GPU-Accelerated Phase-Amplitude Coupling calculation using PyTorch
Author-email: Yusuke Watanabe <ywatanabe@alumni.u-tokyo.ac.jp>
License: MIT
Project-URL: Homepage, https://github.com/ywatanabe1989/gPAC
Project-URL: Repository, https://github.com/ywatanabe1989/gPAC
Keywords: neuroscience,phase-amplitude-coupling,PAC,GPU,PyTorch,signal-processing
Classifier: Development Status :: 4 - Beta
Classifier: Intended Audience :: Science/Research
Classifier: Topic :: Scientific/Engineering :: Medical Science Apps.
Classifier: Topic :: Scientific/Engineering :: Artificial Intelligence
Classifier: License :: OSI Approved :: MIT License
Classifier: Programming Language :: Python :: 3
Classifier: Programming Language :: Python :: 3.8
Classifier: Programming Language :: Python :: 3.9
Classifier: Programming Language :: Python :: 3.10
Classifier: Programming Language :: Python :: 3.11
Classifier: Operating System :: OS Independent
Requires-Python: >=3.8
License-File: LICENSE
Requires-Dist: torch
Requires-Dist: numpy
Requires-Dist: scipy
Requires-Dist: torchaudio
Requires-Dist: matplotlib
Provides-Extra: dev
Requires-Dist: black; extra == "dev"
Requires-Dist: flake8; extra == "dev"
Requires-Dist: isort; extra == "dev"
Provides-Extra: testing
Requires-Dist: pytest; extra == "testing"
Requires-Dist: pytest-cov; extra == "testing"
Requires-Dist: psutil; extra == "testing"
Requires-Dist: tensorpac; extra == "testing"
Requires-Dist: gputil; extra == "testing"
Requires-Dist: mne; extra == "testing"
Provides-Extra: all
Requires-Dist: scikit-learn; extra == "all"
Dynamic: license-file
